LICENSE
README.md
setup.cfg
setup.py
src/magcoilcalc/__init__.py
src/magcoilcalc/_current_sheet.py
src/magcoilcalc/_loop_calc_dennison.py
src/magcoilcalc/_mpl_wrap.py
src/magcoilcalc/_off_axis_loop.py
src/magcoilcalc/_settings.py
src/magcoilcalc/_signals.py
src/magcoilcalc/_version.py
src/magcoilcalc/calculations.py
src/magcoilcalc/core.py
src/magcoilcalc/plotting.py
src/magcoilcalc/templates.py
src/magcoilcalc.egg-info/PKG-INFO
src/magcoilcalc.egg-info/SOURCES.txt
src/magcoilcalc.egg-info/dependency_links.txt
src/magcoilcalc.egg-info/not-zip-safe
src/magcoilcalc.egg-info/requires.txt
src/magcoilcalc.egg-info/top_level.txt