Metadata-Version: 2.1
Name: magcoilcalc
Version: 0.7.3
Summary: Axisymmetric circular current loops field calculator
Home-page: https://github.com/sq-meng/coilcalc
Author: Siqin Meng
Author-email: mengsq04@gmail.com
License: UNKNOWN
Project-URL: Bug Tracker, https://github.com/sq-meng/coilcalc
Platform: UNKNOWN
Classifier: Programming Language :: Python :: 3
Classifier: License :: OSI Approved :: MIT License
Classifier: Operating System :: OS Independent
Requires-Python: >=3.5
License-File: LICENSE
